classtools_autocode/__init__.py
classtools_autocode/autoargs.py
classtools_autocode/autoprops.py
classtools_autocode/class_utils.py
classtools_autocode/utils.py
classtools_autocode/validate.py
classtools_autocode/var_checker.py
classtools_autocode-1.1.0.dist-info/DESCRIPTION.rst
classtools_autocode-1.1.0.dist-info/METADATA
classtools_autocode-1.1.0.dist-info/RECORD
classtools_autocode-1.1.0.dist-info/WHEEL
classtools_autocode-1.1.0.dist-info/metadata.json
classtools_autocode-1.1.0.dist-info/top_level.txt
