Metadata-Version: 2.0
Name: classtools-autocode
Version: 1.1.0
Summary: Helps you write compact python classes
Home-page: https://github.com/smarie/python-classtools-autocode
Author: Sylvain Marié
Author-email: "Sylvain Marié" <sylvain.marie@schneider-electric.com>
License: BSD 3-Clause
Download-URL: https://github.com/smarie/python-classtools-autocode/tarball/1.1.0
Keywords: auto code generator decorator properties fields attributes contract object classes
Platform: UNKNOWN
Classifier: Development Status :: 3 - Alpha
Classifier: Intended Audience :: Developers
Classifier: Topic :: Software Development :: Libraries :: Python Modules
Classifier: License :: OSI Approved :: BSD License
Classifier: Programming Language :: Python :: 3.5
Requires-Dist: decorator
Provides-Extra: contracts
Requires-Dist: PyContracts; extra == 'contracts'
Provides-Extra: enforce
Requires-Dist: enforce; extra == 'enforce'
